MANIFEST.in
README.rst
setup.py
test/test_jd.py
test/test_jslink.py
test/test_suning.py
test/test_tmall.py
test/test_zcgov.py
test/test_zkh.py
zcbot_io_sdk/__init__.py
zcbot_io_sdk.egg-info/PKG-INFO
zcbot_io_sdk.egg-info/SOURCES.txt
zcbot_io_sdk.egg-info/dependency_links.txt
zcbot_io_sdk.egg-info/top_level.txt
zcbot_io_sdk/images/__init__.py
zcbot_io_sdk/images/processor.py
zcbot_io_sdk/utils/__init__.py
zcbot_io_sdk/utils/b64.py